[
    {
        "speaker": "example speaker",
        "text": "「ん、ちゅっ……れぅちゅ……わたしの舌……気持ちいい……？」",
        "translate": "嗯、啾……啊唔啾……我的舌头……舒服吗……？"
    },
    {
        "speaker": "example speaker",
        "text": "「んぅ……よかったぁ……ん、ちゅぢゅ、れぅ……もっとぺろぺろ、してあげゆね……」",
        "translate": "嗯……太好了……嗯，啾啾，啊唔……再给你，舔舔……"
    },
    {
        "speaker": "example speaker",
        "text": "「ふぁ……あふ……エッチなおちんちん……んちゅぅ……つばと、おつゆがまざって……机に、たれてる……」",
        "translate": "呼啊……啊呼……淫荡的欧金金……嗯啾……唾液，和汁液混合在一起……流到桌子上……"
    },
    {
        "speaker": "example speaker",
        "text": "「ん、ぁんっ……！　ペニスから先走り出しすぎだわっ……ひゃぅんんっ！　お尻、ぬるぬるよ……っ」",
        "translate": "嗯……啊……阴茎流出了好多液体啊……呀呜嗯！　屁股，滑滑的…………"
    },
    {
        "speaker": "example speaker",
        "text": "「んくっ、んっ、はぷぅっ、んぷぅぅぅぅぅぅぅっ！！」",
        "translate": "嗯咕，嗯，哈噗，嗯噗呜呜呜呜呜呜！！"
    },
    {
        "speaker": "example speaker",
        "text": "「ぅにゃあぁぁっ、んく、ふぁぁぁぁぁぁぁっ……！！」",
        "translate": "唔呀啊啊啊啊，嗯咕，呼啊啊啊啊啊啊啊啊……！！"
    },
    {
        "speaker": "example speaker",
        "text": "ペニスでショーツを擦れば、くちゅりと愛液が滲みだした。",
        "translate": "用阴茎摩擦着内裤，咕啾一声爱液就渗了出来。"
    },
    {
        "speaker": "example speaker",
        "text": "「んくっ……んっ……ぁあ……やらしい格好、させて……そのうえ、こんな……こんな……」",
        "translate": "嗯咕……嗯……啊啊……让我穿着这种下流的衣服……而且，还是这种……这种……"
    },
    {
        "speaker": "example speaker",
        "text": "「あぁぁぁっ、イくぅ……お尻でちんちん擦ってぇ……んくぅ！　わたしまで、イっちゃうよぉっ……！」",
        "translate": "啊啊啊啊啊……要去了……屁股摩擦着阴茎……嗯咕！　我也，要去了哦……！"
    },
    {
        "speaker": "example speaker",
        "text": "「あああぁぁぁっ！　わ、わたし、ああっ、イくっ……ビクビクしてるの、イきそうなの、ああっ、あぁぁぁっ」",
        "translate": "啊啊啊啊啊！　我，我，啊啊，要去了……一抖一抖的，要高潮了，啊啊，啊啊啊啊！"
    },
    {
        "speaker": "example speaker",
        "text": "「ぁ、あああっ、きて、きてぇっ、一緒にイって、ぁ、ぁぁぁぁ、はぁ、あっ、精液、出してぇぇぇっ……！」",
        "translate": "啊，啊啊啊，出来，出来，一起高潮吧，啊，啊啊啊啊，哈啊，啊，精液，射出来……！"
    },
    {
        "speaker": "example speaker",
        "text": "「ふあああぁぁぁぁぁあぁぁっ、あぁぁぁぁぁっっ！！」",
        "translate": "呼啊啊啊啊啊啊啊，啊啊啊啊啊啊啊！！"
    },
    {
        "speaker": "珠音",
        "text": "「うぅ……服着てても、恥ずかしいよぉ……」",
        "translate": "唔……就算穿着衣服，也感觉好害羞……"
    },
    {
        "speaker": "心の声",
        "text": "珠音は恥ずかしそうに身じろぎした。",
        "translate": "珠音害羞地扭动着身体。"
    },
    {
        "speaker": "良太",
        "text": "「前はもっと露出高かったじゃないか」",
        "translate": "之前不是穿过更加暴露的吗"
    },
    {
        "speaker": "珠音",
        "text": "「そうだけど……はぅぅ……今は、ちょっと事情があるの……」",
        "translate": "这倒没错，哈呜……但是现在，稍微有点那个……"
    },
    {
        "speaker": "良太",
        "text": "「事情？」",
        "translate": "哪个？"
    },
    {
        "speaker": "珠音",
        "text": "「はうぅぅ……あのね、えっと……その、プライベートというか……デリケートというか……」",
        "translate": "哈呜……那个，呃……那个，非常隐私的那种……或者说是，比较敏感的那种……"
    },
    {
        "speaker": "心の声",
        "text": "珠音はもじもじしながら、前屈のように身体を丸めようとする。",
        "translate": "珠音一边扭动着身体，一边试图弯腰。"
    },
    {
        "speaker": "良太",
        "text": "「珠音は恥ずかしがり屋だな」",
        "translate": "珠音是个害羞鬼呢"
    },
    {
        "speaker": "心の声",
        "text": "俺は珠音の前側へ手を回して、身体を反らそうとする。",
        "translate": "我把手伸向珠音的前面，试图让她的身体弯曲。"
    },
    {
        "speaker": "珠音",
        "text": "「やっ……だ、だめっ！　そっちは、絶対だめなの……！」",
        "translate": "不……不，不行！　那边，绝对不行的……！"
    },
    {
        "speaker": "良太",
        "text": "「え？」",
        "translate": "哎？"
    },
    {
        "speaker": "心の声",
        "text": "珠音がハッとしたように抵抗する。",
        "translate": "珠音突然抵抗起来。"
    },
    {
        "speaker": "珠音",
        "text": "「あっ……ごめんね。触られるのが嫌なんじゃなくて、そのぉ……わわ私、恥ずかしくって……！」",
        "translate": "啊……对不起。不是讨厌被触碰，而是那个……我，我害羞……！"
    },
    {
        "speaker": "良太",
        "text": "「珠音が恥ずかしいなら、構わないけど……」",
        "translate": "珠音觉得害羞的话，我不介意的……"
    },
    {
        "speaker": "心の声",
        "text": "ちょっと寂しくなって、俺は珠音の手を掴んだ。",
        "translate": "有点寂寞，我抓住了珠音的手。"
    },
    {
        "speaker": "心の声",
        "text": "女の子らしい華奢な手首が、俺の手の中でふるっと震えた。",
        "translate": "女孩子般纤细的手腕，在我的手中颤抖了一下。"
    },
    {
        "speaker": "珠音",
        "text": "「はぅ……あのね、良くんに触られるのは、嬉しいし気持ちいいの……本当だよ？」",
        "translate": "哈呜……那个，被良君触碰，我很高兴，也很舒服的……真的哦？"
    },
    {
        "speaker": "心の声",
        "text": "珠音はおずおずと呟く。",
        "translate": "珠音小心翼翼地低声说。"
    },
    {
        "speaker": "珠音",
        "text": "「ただ……そのぅ……大好きなの……大好きな人だから……嫌われたくないの」",
        "translate": "只是……那个……因为是喜欢的人……不想被讨厌"
    },
    {
        "speaker": "良太",
        "text": "「珠音のことを嫌いになるはずないだろ？」",
        "translate": "不可能会讨厌珠音的吧？"
    },
    {
        "speaker": "珠音",
        "text": "「う……うんっ、ありがとう……だけど私……あの、身体に、自信なくて……」",
        "translate": "呜……嗯，谢谢……但是我……那个，对身体没什么自信……"
    },
    {
        "speaker": "良太",
        "text": "「そんなこと……珠音の身体はすごく綺麗だよ」",
        "translate": "那种事……珠音的身体很漂亮的"
    },
    {
        "speaker": "心の声",
        "text": "俺は珠音の脚を支えている手で、ゆっくりと太ももを撫でた。",
        "translate": "我用支撑着珠音腿的手，慢慢地抚摸着大腿。"
    },
    {
        "speaker": "良太",
        "text": "「珠音の身体、すべすべしててすごく気持ちいい……白くて、おもちみたいだ……」",
        "translate": "珠音的身体，光滑得很舒服……白皙，像麻糬一样……"
    },
    {
        "speaker": "珠音",
        "text": "「お、おもちっ！？」",
        "translate": "麻，麻糬！？"
    },
    {
        "speaker": "心の声",
        "text": "珠音はぎょっとしたように反応する。",
        "translate": "珠音吓了一跳。"
    },
    {
        "speaker": "良太",
        "text": "「な、なんだ、どうしたんだ？」",
        "translate": "怎，怎么了？"
    },
    {
        "speaker": "珠音",
        "text": "「はぅ……えっと、その……ぷにぷにとか……もちもちとか、そういうことだよね……はぅぅぅぅ……」",
        "translate": "哈呜……那个，那个……软软的，像麻糬一样，那种感觉吧……哈呜呜呜……"
    },
    {
        "speaker": "心の声",
        "text": "なぜか珠音は落ちこんでしまった。",
        "translate": "不知为何，珠音突然低下了头。"
    },
    {
        "speaker": "良太",
        "text": "「ごめん、褒めてるんだ。触り心地がよくて、すごく可愛いって」",
        "translate": "对不起，我在夸你。摸起来很舒服，很可爱的"
    },
    {
        "speaker": "珠音",
        "text": "「うん……うん、分かってるよ。ありがとう……えへへ、可愛いって言ってもらえるのは……嬉しいな」",
        "translate": "嗯……嗯，我知道的。谢谢……呵呵，被说可爱……真是高兴呢"
    },
    {
        "speaker": "心の声",
        "text": "珠音には、なにかデリケートな事情がありそうだ。",
        "translate": "珠音似乎有什么敏感的事情。"
    },
    {
        "speaker": "心の声",
        "text": "俺は珠音の心が少しでも軽くなるように、さらに太ももを撫で回した。",
        "translate": "我为了让珠音的心情再轻松一点，更加抚摸着大腿。"
    },
    {
        "speaker": "心の声",
        "text": "そしてショーツを脱がしていく。",
        "translate": "然后脱掉了内裤。"
    },
    {
        "speaker": "珠音",
        "text": "「ひゃぅ……んっ、んん……気持ち、いい……手……あったかい、ね……」",
        "translate": "呀呜……嗯，嗯……感觉，好……手……暖暖的，呢……"
    },
    {
        "speaker": "心の声",
        "text": "珠音は俺の手が身体の線をなぞっていくのに合わせて、ぴくぴくと身体を震わせた。",
        "translate": "珠音随着我的手在身体上划过的线条，身体抖动了一下。"
    },
    {
        "speaker": "心の声",
        "text": "俺の手に合わせて、珠音が感じてくれている。",
        "translate": "珠音随着我的手，感受着。"
    },
    {
        "speaker": "心の声",
        "text": "普段とは違う、珠音のいやらしい表情を見ているとどんどん興奮してきた。",
        "translate": "看着平时不同的，珠音淫荡的表情，我越来越兴奋。"
    },
    {
        "speaker": "珠音",
        "text": "「ぁっ……おちんちん……か、かたい……ね」",
        "translate": "啊……欧金金……硬，硬硬的……呢"
    },
    {
        "speaker": "良太",
        "text": "「あ、ああ……ごめん」",
        "translate": "啊，啊啊……对不起"
    },
    {
        "speaker": "心の声",
        "text": "無意識のうちに、珠音の秘所にモノを押し当ててしまっていた。",
        "translate": "不知不觉中，我把东西推到了珠音的秘所。"
    },
    {
        "speaker": "珠音",
        "text": "「ふふ、どうして謝るの？」",
        "translate": "呵呵，为什么道歉呢？"
    },
    {
        "speaker": "心の声",
        "text": "これからやらしいことをしようとしてるんだから、勃起するのは当たり前だ。",
        "translate": "因为接下来要做淫荡的事情，勃起是理所当然的。"
    },
    {
        "speaker": "心の声",
        "text": "なんだか急に恥ずかしくなってきた。",
        "translate": "不知怎的，突然觉得害羞了。"
    },
    {
        "speaker": "良太",
        "text": "「いや……なんでもない。珠音が可愛いなって思って……それだけ」",
        "translate": "不……没什么。只是觉得珠音很可爱……就这样"
    },
    {
        "speaker": "珠音",
        "text": "「ひゃぅぅっ……！？　ぁ……りょう、くん……」",
        "translate": "呀呜呜！？　啊……良，君……"
    },
    {
        "speaker": "心の声",
        "text": "今度は意識的に、珠音の秘所にペニスを押しつける。",
        "translate": "这次是有意识地，把阴茎推到珠音的秘所。"
    },
    {
        "speaker": "心の声",
        "text": "くちゅ、という水音と一緒にペニスに湿った感触がする。",
        "translate": "啾，和水声一起，阴茎感觉湿湿的。"
    },
    {
        "speaker": "良太",
        "text": "「珠音、濡れてる……」",
        "translate": "珠音，湿了……"
    },
    {
        "speaker": "珠音",
        "text": "「はわわわわ……恥ずかしい……っ！」",
        "translate": "哈哇哇哇……害羞……！"
    },
    {
        "speaker": "良太",
        "text": "「俺は、濡らしてくれて嬉しいよ」",
        "translate": "我，被弄湿了很高兴的"
    },
    {
        "speaker": "珠音",
        "text": "「ぁんっ……身体、すごく熱くなってきちゃったよぉ……はぁ……あっ……」",
        "translate": "啊啾……身体，变得好热了呢……呼……啊……"
    },
    {
        "speaker": "心の声",
        "text": "珠音の秘穴はペニスを受け入れる準備が整っていた。",
        "translate": "珠音的秘洞准备好接受阴茎了。"
    },
    {
        "speaker": "良太",
        "text": "「そろそろ、いくぞ……」",
        "translate": "差不多，要开始了……"
    },
    {
        "speaker": "珠音",
        "text": "「うん……私のなかに、来てほしいな……お願い……おちんちん、ちょうだい……」",
        "translate": "嗯……想要在我里面……求求你……欧金金，给我……"
    },
    {
        "speaker": "心の声",
        "text": "俺は珠音の秘唇に亀頭を押し当てる。",
        "translate": "我把龟头推到珠音的秘唇。"
    },
    {
        "speaker": "心の声",
        "text": "肉厚な縦筋は亀頭にきつい抵抗を返してきた。",
        "translate": "肉感十足的阴道口紧紧地抵抗着龟头。"
    },
    {
        "speaker": "心の声",
        "text": "俺は腰をぐっと前に押し出した。",
        "translate": "我把腰向前一推。"
    },
    {
        "speaker": "珠音",
        "text": "「んくぅぅぅ……っ！　はぁ、ああんっ……！　あぁ……っおちんちん、はいってきた……」",
        "translate": "嗯咕呜呜……！　呼，啊啊呜……！　啊……欧金金，进来了……"
    },
    {
        "speaker": "心の声",
        "text": "珠音の秘唇が、ぴっちりとペニスを咥え込む。",
        "translate": "珠音的秘唇，紧紧地吞噬着阴茎。"
    },
    {
        "speaker": "心の声",
        "text": "どこか肉厚で柔らかい膣道が、ペニスを包み込んでいく。",
        "translate": "某处肉厚而柔软的阴道，包裹着阴茎。"
    },
    {
        "speaker": "心の声",
        "text": "初めての時は、激しい締め付けにばかり気を取られていたけど、膣道はまるでマシュマロのような柔らかさの粘膜で覆われている。",
        "translate": "第一次的时候，只是被强烈的压迫感所吸引，但阴道却被一层像棉花糖一样柔软的粘膜覆盖着。"
    },
    {
        "speaker": "良太",
        "text": "「すごい……珠音の中、すごく気持ちいいよ」",
        "translate": "好厉害……珠音里面，感觉很舒服的"
    },
    {
        "speaker": "珠音",
        "text": "「えへへ……私の膣内……気に入ってくれて、すごく嬉しいなぁ」",
        "translate": "呵呵……喜欢我的阴道……真是高兴呢"
    },
    {
        "speaker": "良太",
        "text": "「珠音は気持ちいいか？」",
        "translate": "珠音感觉舒服吗？"
    },
    {
        "speaker": "珠音",
        "text": "「うん……すごく気持ちいいよ……おちんちんで、アソコがいっぱいになってて……すごく嬉しいの……」",
        "translate": "嗯……感觉很舒服的……欧金金，把阴道填满了……真是高兴呢……"
    },
    {
        "speaker": "良太",
        "text": "「珠音……」",
        "translate": "珠音……"
    },
    {
        "speaker": "心の声",
        "text": "珠音のいじらしい言葉に、肉棒がますます熱く、硬くなる。",
        "translate": "珠音可爱的话语，让肉棒变得越来越热，越来越硬。"
    },
    {
        "speaker": "珠音",
        "text": "「はぁ……あんっ、気持ちいい……はぁ……あん、おちんちん、あったかい……はふぅ……」",
        "translate": "呼……啊呜，感觉很舒服……呼……啊，欧金金，暖暖的……呼呼……"
    },
    {
        "speaker": "心の声",
        "text": "珠音の秘所は、まだペニスを異物だと認識していて、押し戻そうとしてくる。",
        "translate": "珠音的秘所，还在把阴茎当作异物，试图推开。"
    },
    {
        "speaker": "心の声",
        "text": "絡みつく膣襞をかき分けて、亀頭を押しつけ続ける。",
        "translate": "把缠绕的阴道褶皱分开，继续推压着龟头。"
    },
    {
        "speaker": "珠音",
        "text": "「動きたかったら……動いてもいいんだよ……？　良くん優しいから、遠慮……してない？」",
        "translate": "如果想要动的话……动也没关系的……？　良君很温柔，不用……拘束？"
    },
    {
        "speaker": "良太",
        "text": "「さっき珠音も言ってただろ。くっついてるだけでも幸せなんだよ」",
        "translate": "刚才珠音也说过吧。只是靠在一起就很幸福的"
    },
    {
        "speaker": "珠音",
        "text": "「えへへ……ありがとう。だけど、私で気持ちよくなってくれたら、もっと嬉しいから……」",
        "translate": "呵呵……谢谢。但是，如果能让我感觉舒服，我会更高兴的……"
    },
    {
        "speaker": "良太",
        "text": "「珠音……ありがとう」",
        "translate": "珠音……谢谢"
    },
    {
        "speaker": "心の声",
        "text": "健気な言葉が胸に染みる。",
        "translate": "健康的话语让人感动。"
    },
    {
        "speaker": "心の声",
        "text": "俺は奥深くまで挿入しているペニスをゆっくりと引き抜いた。",
        "translate": "我把插入深处的阴茎慢慢地拔了出来。"
    },
    {
        "speaker": "珠音",
        "text": "「ふぁ、あ、あぅぅ……嬉しい……んんっ……気持ちいい、よぉ……はぁ、あっ……！」",
        "translate": "呼，啊，啊呜呜……高兴……嗯咕……感觉很舒服，呢……呼，啊……！"
    },
    {
        "speaker": "心の声",
        "text": "珠音は身もだえして、太ももを閉じようとする。",
        "translate": "珠音挣扎着，试图闭合大腿。"
    },
    {
        "speaker": "心の声",
        "text": "俺は脚を支える腕に力を込め、抽送を続けながら、豊かな胸を露出させる。",
        "translate": "我用支撑着腿的手臂用力，继续抽送，同时露出丰满的胸部。"
    },
    {
        "speaker": "珠音",
        "text": "「あぅ……ん、はぁぁ……っ！　アソコ、エッチな音……しちゃってるね……ぁ、あぅ……んっ！」",
        "translate": "啊……嗯，呼啊啊……！　阴道，发出淫荡的声音……呢……啊，啊呜……嗯！"
    },
    {
        "speaker": "心の声",
        "text": "厨房内にいやらしい声と音が響く。",
        "translate": "厨房里传来淫荡的声音和声音。"
    },
    {
        "speaker": "珠音",
        "text": "「はぅ……あ、あぅぅん……っ！　厨房、なのに……おちんちん、入っちゃってるね……ぁっ……んん……」",
        "translate": "呼……啊，啊呜呜……！　厨房，明明……欧金金，进来了呢……啊……嗯嗯……"
    },
    {
        "speaker": "心の声",
        "text": "腰を押し出すたびに、珠音のもちもちしたお尻が下腹部に当たって気持ちいい。",
        "translate": "每次推出腰部，珠音的麻糬般的屁股碰到下腹部，感觉很舒服。"
    },
    {
        "speaker": "珠音",
        "text": "「私……この前してもらった時からずっと……こうしてほしいって思ってたんだぁ……」",
        "translate": "我……从上次被做的时候就一直……想要这样的呢……"
    },
    {
        "speaker": "心の声",
        "text": "珠音ははにかみながら告白をする。",
        "translate": "珠音害羞地坦白。"
    },
    {
        "speaker": "心の声",
        "text": "言葉をこぼすたび、珠音の秘所がうねった。",
        "translate": "每说一句话，珠音的秘所就颤动了一下。"
    },
    {
        "speaker": "珠音",
        "text": "「えへへ……だから、すごく嬉しいんだぁ……はぁ、あ……んんっ……」",
        "translate": "呵呵……所以，真的很高兴的呢……呼，啊……嗯咕……"
    },
    {
        "speaker": "良太",
        "text": "「俺だって、すごく嬉しいよ……」",
        "translate": "我也，真的很高兴的……"
    },
    {
        "speaker": "珠音",
        "text": "「ありがと……はぁ、ぅ……その……わ、わたし……自分からお願いできるように……もっと、自信が持てる身体になるね……」",
        "translate": "谢谢……呼，呜……那个……我……为了能够主动请求……会让身体变得更有自信的……"
    },
    {
        "speaker": "良太",
        "text": "「もう十分、自信持っていいと思うけどな」",
        "translate": "我觉得已经足够有自信了"
    },
    {
        "speaker": "心の声",
        "text": "肌は真っ白で、胸が大きくて、抱き締めると柔らかい、女の子らしい身体つきだ。",
        "translate": "皮肤雪白，胸部丰满，抱起来柔软，是典型的女孩子身材。"
    },
    {
        "speaker": "心の声",
        "text": "俺はもう、すっかり魅了されている。",
        "translate": "我已经，完全被迷住了。"
    },
    {
        "speaker": "珠音",
        "text": "「ううんっ……もっと、がんばらないと……私……だ、だから今は……せめて、私の膣内で気持ち良くなってね」",
        "translate": "呜呜呜……要更加努力……我……所以现在……至少，在我的阴道里感觉舒服吧"
    },
    {
        "speaker": "心の声",
        "text": "珠音は健気な腰遣いで、ペニスを刺激しようとしてくる。",
        "translate": "珠音用勇敢的腰部动作，试图刺激阴茎。"
    },
    {
        "speaker": "良太",
        "text": "「ありがとう……俺も、珠音に気持ち良くなってほしい」",
        "translate": "谢谢……我也，希望珠音感觉舒服"
    },
    {
        "speaker": "珠音",
        "text": "「ふわぁ……嬉しい、よぉ……はぁ、あんっ……私は、もう……気持ち、よすぎて……感じすぎちゃってる、からぁ……」",
        "translate": "呜啊……高兴，呢……呼，啊呜……我，已经……感觉，太舒服了……感觉，太强烈了，所以……"
    },
    {
        "speaker": "心の声",
        "text": "珠音の膣内が収縮して、ペニスが押し出されるように抜け出て行く。",
        "translate": "珠音的阴道收缩，阴茎被推出来一样抽出去。"
    },
    {
        "speaker": "心の声",
        "text": "俺は収斂に反して亀頭を押し込み、秘道を開かせた。",
        "translate": "我反而推进龟头，打开了秘道。"
    },
    {
        "speaker": "珠音",
        "text": "「ひゃぅ……ん、はぁっ！　んんっ……気持ちいいよぉ……はぁ、あ……おちんちん、太くて……膣内、拡げられて……」",
        "translate": "呀呜……嗯，呼啊！　嗯咕……感觉很舒服呢……呼，啊……欧金金，太粗了……阴道，被撑开了……"
    },
    {
        "speaker": "心の声",
        "text": "少しでも長く、珠音と繋がっていたい。",
        "translate": "想要和珠音连在一起，哪怕只是一点点。"
    },
    {
        "speaker": "心の声",
        "text": "射精したいのをぐっと抑えて、俺は狭隘を何度も通る。",
        "translate": "强忍着想要射精的冲动，我一次次穿过狭窄的通道。"
    },
    {
        "speaker": "良太",
        "text": "「たしか珠音は、奥が良かったんだよな」",
        "translate": "好像珠音，喜欢深处的吧"
    },
    {
        "speaker": "珠音",
        "text": "「きゃうっ！？　ぁ、ああっ……！　うんっ……気持ちいいの……そこ、奥……気持ちいい……っ！」",
        "translate": "呀呜！？　啊，啊啊……！　嗯咕……感觉很舒服……那里，深处……感觉很舒服……！"
    },
    {
        "speaker": "良太",
        "text": "「やっぱり、ここなんだな……」",
        "translate": "果然，这里吗……"
    },
    {
        "speaker": "心の声",
        "text": "大きく何度も喘ぐ珠音を追い込むように、ピストン運動をする。",
        "translate": "为了迫使大喘气的珠音，我进行了多次抽送。"
    },
    {
        "speaker": "心の声",
        "text": "快感の疼きがどんどん強くなっていく。",
        "translate": "快感的疼痛越来越强烈。"
    },
    {
        "speaker": "珠音",
        "text": "「あぅっ……んくっ、そこぉ……すごい、よ……っ！あんっ、んんっ……！　おちんちん、いっぱいぐりぐり、されて……気持ちいい……っ！」",
        "translate": "啊呜……嗯咕，那里……好厉害……！啊呜，嗯咕……！　欧金金，一直在摩擦……感觉很舒服……！"
    },
    {
        "speaker": "心の声",
        "text": "珠音と体温が混ざり合う快感。",
        "translate": "珠音和体温混合在一起的快感。"
    },
    {
        "speaker": "心の声",
        "text": "悦楽だけじゃなく、充足感や幸福感で心が温かくなる。",
        "translate": "不仅仅是快感，还有满足感和幸福感让心情变得温暖。"
    },
    {
        "speaker": "良太",
        "text": "「珠音の膣内、気持ち良すぎて……うあぁ……っ」",
        "translate": "珠音的阴道，感觉太舒服了……呜啊……！"
    },
    {
        "speaker": "珠音",
        "text": "「ふゃぁぁ……あっ……大好きな人の、おちんちんだから……気持ち良くなってほしいの……いっぱい、気持ちよく、なってほしくて……」",
        "translate": "呜啊啊……啊……因为是喜欢的人的，欧金金……想要感觉舒服……想要感觉很舒服……"
    },
    {
        "speaker": "珠音",
        "text": "「だから、いっぱい……ぎゅぅって、抱き締めたくなるの、はぁ、うぅ……アソコが、喜んで、うずいて……大好きって、言ってるの……」",
        "translate": "所以，想要抱紧，想要抱紧，呼，呜……阴道，高兴地，颤动着……喜欢你，这样说的……"
    },
    {
        "speaker": "良太",
        "text": "「そういう……可愛いこと、言われたら……っ！」",
        "translate": "这样……被说可爱的话……！"
    },
    {
        "speaker": "心の声",
        "text": "もう、止まれなくなる。",
        "translate": "已经，无法停下来了。"
    },
    {
        "speaker": "珠音",
        "text": "「ふゃっ、あっ、んくぅっ……！　おちんちん、膣内で跳ねてっ……あ、あ、すごいっ……熱いよぉっ……！」",
        "translate": "呜啊，啊，嗯咕……！　欧金金，在阴道里跳动……啊，啊，好厉害……好热呢……！"
    },
    {
        "speaker": "心の声",
        "text": "カリ首でヒダを引っかくように腰を回すと、珠音が大きく跳ねる。",
        "translate": "用龟头刮擦褶皱一样回旋腰部，珠音大幅度地跳动。"
    },
    {
        "speaker": "良太",
        "text": "「ごめん、珠音……可愛すぎて……っ！」",
        "translate": "对不起，珠音……太可爱了……！"
    },
    {
        "speaker": "心の声",
        "text": "穿つように腰を突き入れ、舐め回すように肉棒を引き抜く。",
        "translate": "像刺穿一样推进腰部，像舔舐一样抽出肉棒。"
    },
    {
        "speaker": "珠音",
        "text": "「はぅっ、あっ、ふあぁぁぁ……！　コンコンって、されて……あ、んはぅっ！　気持ちよすぎるよぉ……っ」",
        "translate": "呼呜，啊，呜啊啊啊……！　咚咚地，被……啊，嗯呜！　感觉太舒服了呢……！"
    },
    {
        "speaker": "心の声",
        "text": "珠音の乳房が大きくバウンドするのが見える。",
        "translate": "可以看到珠音的乳房大幅度地弹跳。"
    },
    {
        "speaker": "心の声",
        "text": "直接揉みしだきたい感情を抑えて、結合を深くした。",
        "translate": "抑制住想要直接揉捏的感情，深入结合。"
    },
    {
        "speaker": "良太",
        "text": "「珠音の身体、温かくて、柔らかくて……気持ちいい」",
        "translate": "珠音的身体，温暖而柔软……感觉很舒服"
    },
    {
        "speaker": "珠音",
        "text": "「や、柔らかい……っ！？」",
        "translate": "软，软绵绵的……！？"
    },
    {
        "speaker": "良太",
        "text": "「ああ……温かくて、すごく気持ちいい」",
        "translate": "啊啊……温暖而，感觉很舒服"
    },
    {
        "speaker": "珠音",
        "text": "「そっかぁ……気持ち、いいなら……嬉しいな……はぅ、んぅぅ……っ！」",
        "translate": "这样啊……感觉，很舒服的话……真是高兴呢……呼，嗯呜呜……！"
    },
    {
        "speaker": "心の声",
        "text": "珠音がまた、恥らうように身体を丸めようとした。",
        "translate": "珠音又一次，害羞地把身体卷起来。"
    },
    {
        "speaker": "心の声",
        "text": "その分の距離を詰めるように、俺はさらに身体を密着させる。",
        "translate": "为了缩短这段距离，我更加贴近身体。"
    },
    {
        "speaker": "珠音",
        "text": "「はうんっ……！　ぁ、あふ……っ！　身体……わたし、い、いま……汗で……っ！」",
        "translate": "呜呜……！　啊，啊呜……！　身体……我，现在……汗水……！"
    },
    {
        "speaker": "良太",
        "text": "「そんなの、お互いさまだ……」",
        "translate": "这种事，是互相的……"
    },
    {
        "speaker": "心の声",
        "text": "俺は珠音の首筋に鼻をうずめる。",
        "translate": "我把鼻子贴在珠音的脖子上。"
    },
    {
        "speaker": "良太",
        "text": "「それに、すごく良い匂いだ」",
        "translate": "而且，味道很好"
    },
    {
        "speaker": "珠音",
        "text": "「はぅぅっ……でも、でもっ……恥ずかしい……よぉ……ぁ、あああっ……ん、んくぅぅっ……！」",
        "translate": "呼呜……但是，但是……害羞……呢……啊，啊啊啊……嗯，嗯咕……！"
    },
    {
        "speaker": "心の声",
        "text": "珠音は身悶えしながらも、俺が息を吸い込むたびに膣肉を引き締める。",
        "translate": "珠音虽然身体扭动，但每次我吸气的时候，阴道肌肉就会收紧。"
    },
    {
        "speaker": "心の声",
        "text": "恥じらいも珠音の快感を盛り立てる一因なんだと思うと、興奮が増した。",
        "translate": "想到害羞也是增加珠音快感的原因，兴奋增加了。"
    },
    {
        "speaker": "心の声",
        "text": "突き入れるたび、珠音の身体がずり上がっていく。",
        "translate": "每次推进，珠音的身体就会往上滑动。"
    },
    {
        "speaker": "心の声",
        "text": "逃げていってしまいそうな身体を押さえて、ペニスを根元まで咥えさせる。",
        "translate": "抓住似乎要逃跑的身体，让阴茎吞没到根部。"
    },
    {
        "speaker": "珠音",
        "text": "「あっ、ああんっ……！　奥、すごい……深くまで、きてる……ぁ、ああっ……赤ちゃんのお部屋に……届いてる……っ！」",
        "translate": "啊，啊呜……！　深处，好厉害……已经到了深处……啊，啊啊……到了宝宝的房间……！"
    },
    {
        "speaker": "心の声",
        "text": "快感が高まってきた証のように、珠音の奥が狭くなる。",
        "translate": "快感增加的证据，珠音的深处变得更加狭窄。"
    },
    {
        "speaker": "心の声",
        "text": "亀頭に当たる感触が熱く、そして潤みきっている。",
        "translate": "龟头碰到的感觉很热，而且很湿润。"
    },
    {
        "speaker": "良太",
        "text": "「そうだな……奥まで届いてる……っ！」",
        "translate": "是啊……已经到了深处……！"
    },
    {
        "speaker": "心の声",
        "text": "俺はまっすぐペニスを挿入して、膣奥を叩いた。",
        "translate": "我直插阴茎，击打阴道深处。"
    },
    {
        "speaker": "珠音",
        "text": "「ふゃぁっ！　ぁっ、あ……赤ちゃんのお部屋……っ！そこ、気持ちいいの……」",
        "translate": "呜啊！　啊，啊……宝宝的房间……！那里，感觉很舒服……"
    },
    {
        "speaker": "良太",
        "text": "「そっか。それじゃあ、もっとするな」",
        "translate": "这样啊。那么，就更多地做吧"
    },
    {
        "speaker": "心の声",
        "text": "ビクビク跳ねる珠音の腰を力ずくで押さえこんで抽送を続ける。",
        "translate": "抓住抖动的珠音的腰部，强行抽送。"
    },
    {
        "speaker": "心の声",
        "text": "膣壁を斜めにえぐるたび、珠音は甘い声をあげる。",
        "translate": "每次斜斜地刮膣壁，珠音都会发出甜美的声音。"
    },
    {
        "speaker": "珠音",
        "text": "「はぅ、あぅぅん……気持ちいいよぉ……気持ちいい……あんっ、ぁっ……おなか、あつい……ん、んっ……きゅんって、してる……！」",
        "translate": "呼，啊呜呜……感觉很舒服呢……感觉很舒服……啊呜，啊……肚子，好热……嗯，嗯咕……酸酸的，感觉……！"
    },
    {
        "speaker": "心の声",
        "text": "珠音の色白な肌が波打つ。",
        "translate": "珠音雪白的皮肤波动着。"
    },
    {
        "speaker": "心の声",
        "text": "いやらしい匂いが全身から放たれているかのように、興奮が頂点を目指して急激に高まり始める。",
        "translate": "就像从全身散发出淫荡的气味一样，兴奋开始急剧上升，以达到顶点。"
    },
    {
        "speaker": "珠音",
        "text": "「ふゃぁっ……すごいよ、こんなの、ぁぁっ……すごい、アソコが、おかしくなっちゃうぅ……っ！」",
        "translate": "呜啊……好厉害，这样的，啊啊……好厉害，阴道，要变成奇怪的呢……！"
    },
    {
        "speaker": "心の声",
        "text": "珠音の乱れてる姿は、生唾を呑むほど淫靡だった。",
        "translate": "珠音混乱的样子，让人垂涎三尺。"
    },
    {
        "speaker": "心の声",
        "text": "いつも優しく微笑みながら、この厨房で料理をしてる珠音なのに。",
        "translate": "平时总是微笑着温柔地在厨房里做饭的珠音。"
    },
    {
        "speaker": "心の声",
        "text": "今は乳房を揺らしながら、激しく身悶えて絶頂しようとしている。",
        "translate": "现在，她摇动着乳房，剧烈地扭动着身体，试图达到高潮。"
    },
    {
        "speaker": "珠音",
        "text": "「ふぁぁぁっ、あぅぅん……っ！　気持ち、いいよぉ……もう……だめに、なっちゃう……アソコ、だめになっちゃうよぉ……！」",
        "translate": "呜啊啊啊，啊呜呜……！　感觉，很舒服呢……已经……要坏掉了……阴道，要坏掉了呢……！"
    },
    {
        "speaker": "良太",
        "text": "「そのままずっと、感じてくれ……っ」",
        "translate": "就这样一直，感觉吧……！"
    },
    {
        "speaker": "心の声",
        "text": "俺は抽送の角度を変えて、珠音の感じそうな場所を何度も叩く。",
        "translate": "我改变抽送的角度，多次击打珠音感觉到的地方。"
    },
    {
        "speaker": "珠音",
        "text": "「ひゃうぅっ！　あんっ！　気持ち、いいよぉ……！あんっ、おちんちん、いろんなところに、当たってぇ……気持ちいい……！」",
        "translate": "呀呜呜！　啊呜！　感觉，很舒服呢……！啊呜，欧金金，到处都碰到了……感觉很舒服……！"
    },
    {
        "speaker": "心の声",
        "text": "珠音の膣肉が激しく震えだして、熱い蜜の粘り気が濃くなる。",
        "translate": "珠音的阴道肌肉剧烈地颤抖，热蜜的粘稠度增加。"
    },
    {
        "speaker": "心の声",
        "text": "白っぽい本気汁が、秘裂から垂れ落ちる。",
        "translate": "白色的真正汁液，从秘裂中滴落。"
    },
    {
        "speaker": "良太",
        "text": "「珠音、そろそろイきそう……？」",
        "translate": "珠音，快要高潮了……？"
    },
    {
        "speaker": "珠音",
        "text": "「ふゃ、ああぅっ……分かっちゃう、の……？　んん、はずかしい、よぉぅ……！」",
        "translate": "呜，啊呜呜……知道了，吗……？　嗯咕，害羞，呢……！"
    },
    {
        "speaker": "良太",
        "text": "「いいよ、恥ずかしがらなくて……」",
        "translate": "没关系，不用害羞……"
    },
    {
        "speaker": "心の声",
        "text": "亀頭を最奥に押し込むと、珠音の背筋がぶるんと震えた。",
        "translate": "把龟头推到最深处，珠音的背脊颤抖了一下。"
    },
    {
        "speaker": "珠音",
        "text": "「うぅ、ああ……らめぇ……はぁ、ああっ……きもちいい、きもちいいよぉ……っ！」",
        "translate": "呜，啊……不要……呼，啊啊……感觉很舒服，感觉很舒服呢……！"
    },
    {
        "speaker": "心の声",
        "text": "昂ぶって身悶えている珠音の膣肉に、ペニスはもみくちゃにされている。",
        "translate": "兴奋地扭动着身体的珠音的阴道肌肉，阴茎被揉成了一团。"
    },
    {
        "speaker": "心の声",
        "text": "痺れるような快感が、腰奥からだんだんと昇ってきていた。",
        "translate": "麻痹般的快感，从腰部慢慢上升。"
    },
    {
        "speaker": "良太",
        "text": "「珠音、俺もう……」",
        "translate": "珠音，我已经……"
    },
    {
        "speaker": "珠音",
        "text": "「うんっ、イってぇ……私も、イっちゃいそう、なの……アソコ、熱くなっちゃって……はぁ、だめ、なの……っ」",
        "translate": "嗯，要高潮了……我也，要高潮了……阴道，变得很热……呼，不行，了……！"
    },
    {
        "speaker": "心の声",
        "text": "珠音の中が激しくうねって、精液を絞り取る準備を始めている。",
        "translate": "珠音的里面剧烈地扭动着，开始准备挤出精液。"
    },
    {
        "speaker": "心の声",
        "text": "もう珠音の膣内から抜くことなんて考えられなかった。",
        "translate": "已经无法想象从珠音的阴道里抽出来。"
    },
    {
        "speaker": "良太",
        "text": "「珠音、俺このままっ……！」",
        "translate": "珠音，我就这样……！"
    },
    {
        "speaker": "珠音",
        "text": "「うんっ、お願い……私のなかで、射精してぇ……はぁ、あうぅぅんっ……私の、なかでぇ……一緒に、イってぇ……っ！」",
        "translate": "嗯，求求你……在我里面，射精……呼，啊呜呜……在我里面……一起，高潮……！"
    },
    {
        "speaker": "心の声",
        "text": "珠音はこくこく頷き、無意識なのか膣内をぎゅうぅっと引き締めた。",
        "translate": "珠音点点头，不知不觉地收紧了阴道。"
    },
    {
        "speaker": "珠音",
        "text": "「ん……あぁぁっ、らめ、らめぇっ……こんなの、あぅ、おかしくなっちゃう、アソコぐしゃぐしゃになるぅ、ぁ、あ、あ、らめらよぉ……っ！」",
        "translate": "嗯……啊啊，不要，不要……这样的，啊，要变成奇怪的，阴道变得湿湿的，啊，啊，不要不要……！"
    },
    {
        "speaker": "心の声",
        "text": "脚を押さえつけ、思い切りペニスを突き入れる。",
        "translate": "按住脚，狠狠地插入阴茎。"
    },
    {
        "speaker": "珠音",
        "text": "「あぁぁぁぁぁんっ、あっ、も、イく、イくよぉっ！もう、だめぇっ……ふやぁんっ！　イっちゃう、イっちゃうよぉぉ……っ！！」",
        "translate": "啊啊啊啊啊呜，啊，要，要高潮了！已经，不行了……呜呜呜！　要高潮了，要高潮了呜呜……！！"
    },
    {
        "speaker": "珠音",
        "text": "「んきゅぅぅぅぅうううっ！　はぅぅ、ぁっ、ふやぁぁぁ、ふぁぁぁあああああっ！！」",
        "translate": "嗯呜呜呜呜呜呜呜！　呼呜，啊，呜呜呜，呜呜呜呜呜呜呜！！"
    },
    {
        "speaker": "心の声",
        "text": "突き入れたペニスから、激しく吐精した。",
        "translate": "插入的阴茎，猛烈地射精。"
    },
    {
        "speaker": "心の声",
        "text": "ドクドク震えるペニスが、痙攣する膣襞で擦られる。",
        "translate": "滴滴答答颤抖的阴茎，被痉挛的阴道褶皱擦着。"
    },
    {
        "speaker": "珠音",
        "text": "「ふやぁ、ああっ、あふれちゃう、赤ちゃんのお部屋、精子で、いっぱいになる、なっちゃうよぉっ！」",
        "translate": "呜呜，啊啊，溢出来了，宝宝的房间，精子，满满的，要满了呜呜！"
    },
    {
        "speaker": "心の声",
        "text": "珠音の子宮口めがけて、精液はどんどん溢れていった。",
        "translate": "精液朝着珠音的子宫口，不断地溢出。"
    },
    {
        "speaker": "珠音",
        "text": "「ふゃ……あ、はぁ……えへへ……おなかにいっぱい、精液そそがれちゃった、ね……ふゃぁ……」",
        "translate": "呜……啊，呼……嘿嘿……肚子里满满的，精液都流了进去，呢……呜……"
    },
    {
        "speaker": "良太",
        "text": "「ごめん……そうだな」",
        "translate": "对不起……是啊"
    },
    {
        "speaker": "心の声",
        "text": "へら、と幸せそうに微笑む珠音があまりにも可愛くて、ついぶっきらぼうに頷いてしまった。",
        "translate": "呵呵，幸福地微笑着的珠音太可爱了，不由得粗鲁地点了点头。"
    },
    {
        "speaker": "良太",
        "text": "「珠音、もうイきそうだ……っ」",
        "translate": "珠音，我快要高潮了……！"
    },
    {
        "speaker": "心の声",
        "text": "抽送しながら耳元でささやくと、珠音はゾクゾクと背中を震わせた。",
        "translate": "一边抽送一边在耳边低声说话，珠音的背部颤抖了起来。"
    },
    {
        "speaker": "珠音",
        "text": "「ふぁぁっ！　わた……わたしも、イっちゃいそうなの……はぁ、ああっ、アソコがね、あつくてぇ……あ、あっ、おかしくなっちゃいそう、なのぉ……！」",
        "translate": "呜啊！　我……我也，要高潮了……呼，啊啊，阴道呢，很热呢……啊，啊，要变成奇怪的呢……！"
    },
    {
        "speaker": "心の声",
        "text": "膣内がうねり、愛液が肉竿に染みこむような感覚に意識が溶けそうになる。",
        "translate": "阴道内扭动，爱液渗透到肉棒上的感觉，让意识快要溶化。"
    },
    {
        "speaker": "心の声",
        "text": "珠音の身体も限界が近付いてきたようで、汗まみれのお尻がビクビク震えた。",
        "translate": "珠音的身体也接近极限，汗水浸透的屁股颤抖着。"
    },
    {
        "speaker": "珠音",
        "text": "「はぁっ、あっ、んひゃぅぅぅ……だめ、だよぉっ……おちんちん、硬くて、きもちいいの……いっぱいになっちゃう……はう、んんぅっ！」",
        "translate": "呼，啊，嗯呜呜……不行，不行呢……欧金金，硬硬的，感觉很舒服呢……要满了……呼，嗯咕呜！"
    },
    {
        "speaker": "心の声",
        "text": "珠音の蕩けきった口から、快感の声とよだれが溢れ出す。",
        "translate": "从珠音迷醉的嘴里，溢出了快感的声音和口水。"
    },
    {
        "speaker": "珠音",
        "text": "「ひゃぅぅぅぅ、ああ、あひぅっ、も、だめ、だめぇっ、んくっ、ああぁ！　イっちゃう、イっちゃうよぉ……はぁ、ぁあああっ！」",
        "translate": "呜呜呜呜，啊，啊呜呜，要，不行，不行呜呜，嗯咕，啊啊！　要高潮了，要高潮了呜呜……呼，啊啊啊！"
    },
    {
        "speaker": "心の声",
        "text": "強く引き締まった膣内から、ペニスを引き抜いていく。",
        "translate": "从紧紧收紧的阴道里抽出阴茎。"
    },
    {
        "speaker": "流用/珠音",
        "text": "「あぁぁぁぁぁんっ、あっ、も、イく、イくよぉっ！もう、だめぇっ……ふやぁんっ！　イっちゃう、イっちゃうよぉぉ……っ！！」",
        "translate": "啊啊啊啊啊呜，啊，要，要高潮了！已经，不行了……呜呜呜！　要高潮了，要高潮了呜呜……！！"
    },
    {
        "speaker": "流用/珠音",
        "text": "「んきゅぅぅぅぅうううっ！　はぅぅ、ぁっ、ふやぁぁぁ、ふぁぁぁあああああっ！！」",
        "translate": "嗯呜呜呜呜呜呜呜！　呼呜，啊，呜呜呜，呜呜呜呜呜呜呜！！"
    },
    {
        "speaker": "心の声",
        "text": "ペニスを引き抜いた蜜穴から、愛液が飛び散る。",
        "translate": "从抽出的蜜穴里，爱液飞溅出来。"
    },
    {
        "speaker": "珠音",
        "text": "「あっあっ……ふああぁぁぁ……！　せいえき、すごい、すごい、いきおいでっ……あ、あ、こんなに熱いの、わたし……感じすぎちゃう、よぉっ……！」",
        "translate": "啊啊……呼啊啊啊……！　精液，好厉害，好厉害，冲出来了……啊，啊，这么热，我……感觉太多了，呜呜！"
    },
    {
        "speaker": "心の声",
        "text": "対抗するように、俺のペニスからも精液が激しく溢れた。",
        "translate": "对抗着，我的阴茎也猛烈地溢出精液。"
    },
    {
        "speaker": "心の声",
        "text": "白濁液が、台に飛び散った珠音の愛液と混ざる。",
        "translate": "白浊液，和飞溅到台上的珠音的爱液混合在一起。"
    },
    {
        "speaker": "珠音",
        "text": "「はふ……気持ち良かった……ね、えへへ……私の身体、良くんの匂いでいっぱいだぁ」",
        "translate": "呼呼……感觉很好……呢，嘿嘿……我的身体，充满了良太的味道呢"
    },
    {
        "speaker": "良太",
        "text": "「そうだな」",
        "translate": "是啊"
    },
    {
        "speaker": "心の声",
        "text": "はにかんで微笑む珠音があまりにも可愛くて、ついぶっきらぼうな受け答えになってしまった。",
        "translate": "害羞地微笑的珠音太可爱了，不由得粗鲁地回答了。"
    },
    {
        "speaker": "珠音",
        "text": "「台、大変なことになっちゃったね……」",
        "translate": "台子，变成了很糟糕的样子呢……"
    },
    {
        "speaker": "良太",
        "text": "「ああ、これはちょっと……我ながらすさまじいな……」",
        "translate": "啊啊，这个有点……我自己也觉得很厉害……"
    },
    {
        "speaker": "心の声",
        "text": "見下ろす天板は、二人分の体液でドロドロになっていた。",
        "translate": "俯视下去的天板，被两个人的体液弄得黏糊糊的。"
    },
    {
        "speaker": "珠音",
        "text": "「ちゃんと綺麗にしておかないと……お母さんたちに、分かっちゃうね」",
        "translate": "不好好清理一下的话……妈妈们会发现的呢"
    },
    {
        "speaker": "良太",
        "text": "「朝までにしっかり掃除しておけば大丈夫だろう、多分」",
        "translate": "如果在早上之前好好清理一下的话应该没问题，大概"
    },
    {
        "speaker": "珠音",
        "text": "「じゃあ、えっと……せっかくだから換気とかだけじゃなくて、いろいろ……床も全部、ぴかぴかにしちゃおっか」",
        "translate": "那么，呃……既然这样，不仅仅是通风，还有其他的……地板也全部擦干净吧"
    },
    {
        "speaker": "良太",
        "text": "「ちょっと待ってくれ」",
        "translate": "等等我"
    },
    {
        "speaker": "心の声",
        "text": "俺は珠音の言葉を遮り、後ろから抱きしめる。",
        "translate": "我打断了珠音的话，从后面抱住了她。"
    },
    {
        "speaker": "心の声",
        "text": "俺と珠音は、テーブルの上でしばらく寄り添い続けた。",
        "translate": "我和珠音，在桌子上依偎在一起。"
    },
    {
        "speaker": "心の声",
        "text": "体温の高ぶりはなかなか収まらず、離れる気にもなれない。",
        "translate": "体温的高涨不容易平息，也无法离开。"
    },
    {
        "speaker": "珠音",
        "text": "「えへへ……くっついてるの、幸せだね」",
        "translate": "嘿嘿……贴在一起，好幸福呢"
    },
    {
        "speaker": "良太",
        "text": "「そうだな、すごく幸せだ……」",
        "translate": "是啊，好幸福……"
    },
    {
        "speaker": "心の声",
        "text": "珠音の肩口に額を押しつけると、甘い汗の香りがした。",
        "translate": "把额头贴在珠音的肩膀上，闻到了甜蜜的汗味。"
    },
    {
        "speaker": "心の声",
        "text": "いっそこのまま眠ってしまいたくなるくらい心地良い。",
        "translate": "真想就这样睡着，这样舒服。"
    },
    {
        "speaker": "珠音",
        "text": "「もう少しだけでいいから、こうしてたいな……」",
        "translate": "再多一点点就好了，这样一直贴着……"
    },
    {
        "speaker": "良太",
        "text": "「俺もだ。まだ夜も更けたばかりだから、大丈夫だよ」",
        "translate": "我也是。夜还没过去，没关系的"
    },
    {
        "speaker": "心の声",
        "text": "幸せそうな声に俺の心まで溶かされそうに感じながら、しばらく体温を交換し合った。",
        "translate": "被幸福的声音感动得心都要融化了，我们交换了一会儿体温。"
    }
]